tutorial_hypermodern_python_winand/__init__.py
tutorial_hypermodern_python_winand/console.py
tutorial_hypermodern_python_winand/wikipedia.py
tutorial_hypermodern_python_winand-0.1.0.dist-info/METADATA
tutorial_hypermodern_python_winand-0.1.0.dist-info/entry_points.txt
tutorial_hypermodern_python_winand-0.1.0.dist-info/WHEEL
tutorial_hypermodern_python_winand-0.1.0.dist-info/LICENSE
tutorial_hypermodern_python_winand-0.1.0.dist-info/RECORD
